{
  "evaluation_parameters": {},
  "meta": {
    "active_batch_definition": {
      "batch_identifiers": {},
      "data_asset_name": "jaffle_shop.customers",
      "data_connector_name": "default_inferred_data_connector_name",
      "datasource_name": "jaffle_shop"
    },
    "batch_markers": {
      "ge_load_time": "20220518T173313.311162Z"
    },
    "batch_spec": {
      "batch_identifiers": {},
      "data_asset_name": "jaffle_shop.customers",
      "schema_name": "jaffle_shop",
      "table_name": "customers",
      "type": "table"
    },
    "expectation_suite_name": "jaffle_shop.customers.warning",
    "great_expectations_version": "0.15.5",
    "run_id": {
      "run_name": null,
      "run_time": "2022-05-18T14:33:13.276807+00:00"
    },
    "validation_time": "20220518T173313.378381Z"
  },
  "results": [
    {
      "exception_info": {
        "exception_message": null,
        "exception_traceback": null,
        "raised_exception": false
      },
      "expectation_config": {
        "expectation_type": "expect_table_columns_to_match_ordered_list",
        "kwargs": {
          "batch_id": "216a12aaad3601d000c11f462f93d1e9",
          "column_list": [
            "id",
            "first_name",
            "last_name"
          ]
        },
        "meta": {}
      },
      "meta": {},
      "result": {
        "observed_value": [
          "id",
          "first_name",
          "last_name"
        ]
      },
      "success": true
    },
    {
      "exception_info": {
        "exception_message": null,
        "exception_traceback": null,
        "raised_exception": false
      },
      "expectation_config": {
        "expectation_type": "expect_table_row_count_to_be_between",
        "kwargs": {
          "batch_id": "216a12aaad3601d000c11f462f93d1e9",
          "max_value": 100,
          "min_value": 100
        },
        "meta": {}
      },
      "meta": {},
      "result": {
        "observed_value": 100
      },
      "success": true
    },
    {
      "exception_info": {
        "exception_message": null,
        "exception_traceback": null,
        "raised_exception": false
      },
      "expectation_config": {
        "expectation_type": "expect_column_min_to_be_between",
        "kwargs": {
          "batch_id": "216a12aaad3601d000c11f462f93d1e9",
          "column": "id",
          "max_value": 1,
          "min_value": 1
        },
        "meta": {}
      },
      "meta": {},
      "result": {
        "observed_value": 1
      },
      "success": true
    },
    {
      "exception_info": {
        "exception_message": null,
        "exception_traceback": null,
        "raised_exception": false
      },
      "expectation_config": {
        "expectation_type": "expect_column_max_to_be_between",
        "kwargs": {
          "batch_id": "216a12aaad3601d000c11f462f93d1e9",
          "column": "id",
          "max_value": 100,
          "min_value": 100
        },
        "meta": {}
      },
      "meta": {},
      "result": {
        "observed_value": 100
      },
      "success": true
    },
    {
      "exception_info": {
        "exception_message": null,
        "exception_traceback": null,
        "raised_exception": false
      },
      "expectation_config": {
        "expectation_type": "expect_column_mean_to_be_between",
        "kwargs": {
          "batch_id": "216a12aaad3601d000c11f462f93d1e9",
          "column": "id",
          "max_value": 50.5,
          "min_value": 50.5
        },
        "meta": {}
      },
      "meta": {},
      "result": {
        "observed_value": 50.5
      },
      "success": true
    },
    {
      "exception_info": {
        "exception_message": null,
        "exception_traceback": null,
        "raised_exception": false
      },
      "expectation_config": {
        "expectation_type": "expect_column_median_to_be_between",
        "kwargs": {
          "batch_id": "216a12aaad3601d000c11f462f93d1e9",
          "column": "id",
          "max_value": 50.5,
          "min_value": 50.5
        },
        "meta": {}
      },
      "meta": {},
      "result": {
        "observed_value": 50.5
      },
      "success": true
    },
    {
      "exception_info": {
        "exception_message": null,
        "exception_traceback": null,
        "raised_exception": false
      },
      "expectation_config": {
        "expectation_type": "expect_column_quantile_values_to_be_between",
        "kwargs": {
          "allow_relative_error": true,
          "batch_id": "216a12aaad3601d000c11f462f93d1e9",
          "column": "id",
          "quantile_ranges": {
            "quantiles": [
              0.05,
              0.25,
              0.5,
              0.75,
              0.95
            ],
            "value_ranges": [
              [
                5,
                5
              ],
              [
                25,
                25
              ],
              [
                50,
                50
              ],
              [
                75,
                75
              ],
              [
                95,
                95
              ]
            ]
          }
        },
        "meta": {}
      },
      "meta": {},
      "result": {
        "details": {
          "success_details": [
            true,
            true,
            true,
            true,
            true
          ]
        },
        "observed_value": {
          "quantiles": [
            0.05,
            0.25,
            0.5,
            0.75,
            0.95
          ],
          "values": [
            5,
            25,
            50,
            75,
            95
          ]
        }
      },
      "success": true
    },
    {
      "exception_info": {
        "exception_message": null,
        "exception_traceback": null,
        "raised_exception": false
      },
      "expectation_config": {
        "expectation_type": "expect_column_values_to_not_be_null",
        "kwargs": {
          "batch_id": "216a12aaad3601d000c11f462f93d1e9",
          "column": "id"
        },
        "meta": {}
      },
      "meta": {},
      "result": {
        "element_count": 100,
        "partial_unexpected_counts": [],
        "partial_unexpected_index_list": null,
        "partial_unexpected_list": [],
        "unexpected_count": 0,
        "unexpected_percent": 0.0
      },
      "success": true
    },
    {
      "exception_info": {
        "exception_message": null,
        "exception_traceback": null,
        "raised_exception": false
      },
      "expectation_config": {
        "expectation_type": "expect_column_proportion_of_unique_values_to_be_between",
        "kwargs": {
          "batch_id": "216a12aaad3601d000c11f462f93d1e9",
          "column": "id",
          "max_value": 1.0,
          "min_value": 1.0
        },
        "meta": {}
      },
      "meta": {},
      "result": {
        "observed_value": 1.0
      },
      "success": true
    },
    {
      "exception_info": {
        "exception_message": null,
        "exception_traceback": null,
        "raised_exception": false
      },
      "expectation_config": {
        "expectation_type": "expect_column_values_to_be_in_type_list",
        "kwargs": {
          "batch_id": "216a12aaad3601d000c11f462f93d1e9",
          "column": "id",
          "type_list": [
            "INTEGER",
            "integer",
            "int",
            "int_",
            "int8",
            "int16",
            "int32",
            "int64",
            "uint8",
            "uint16",
            "uint32",
            "uint64",
            "Int8Dtype",
            "Int16Dtype",
            "Int32Dtype",
            "Int64Dtype",
            "UInt8Dtype",
            "UInt16Dtype",
            "UInt32Dtype",
            "UInt64Dtype",
            "INT",
            "INTEGER",
            "INT64",
            "TINYINT",
            "BYTEINT",
            "SMALLINT",
            "BIGINT",
            "IntegerType",
            "LongType"
          ]
        },
        "meta": {}
      },
      "meta": {},
      "result": {
        "observed_value": "INTEGER"
      },
      "success": true
    },
    {
      "exception_info": {
        "exception_message": null,
        "exception_traceback": null,
        "raised_exception": false
      },
      "expectation_config": {
        "expectation_type": "expect_column_values_to_not_be_null",
        "kwargs": {
          "batch_id": "216a12aaad3601d000c11f462f93d1e9",
          "column": "first_name"
        },
        "meta": {}
      },
      "meta": {},
      "result": {
        "element_count": 100,
        "partial_unexpected_counts": [],
        "partial_unexpected_index_list": null,
        "partial_unexpected_list": [],
        "unexpected_count": 0,
        "unexpected_percent": 0.0
      },
      "success": true
    },
    {
      "exception_info": {
        "exception_message": null,
        "exception_traceback": null,
        "raised_exception": false
      },
      "expectation_config": {
        "expectation_type": "expect_column_proportion_of_unique_values_to_be_between",
        "kwargs": {
          "batch_id": "216a12aaad3601d000c11f462f93d1e9",
          "column": "first_name",
          "max_value": 0.79,
          "min_value": 0.79
        },
        "meta": {}
      },
      "meta": {},
      "result": {
        "observed_value": 0.79
      },
      "success": true
    },
    {
      "exception_info": {
        "exception_message": null,
        "exception_traceback": null,
        "raised_exception": false
      },
      "expectation_config": {
        "expectation_type": "expect_column_values_to_be_in_type_list",
        "kwargs": {
          "batch_id": "216a12aaad3601d000c11f462f93d1e9",
          "column": "first_name",
          "type_list": [
            "CHAR",
            "NCHAR",
            "VARCHAR",
            "NVARCHAR",
            "TEXT",
            "NTEXT",
            "STRING",
            "StringType",
            "string",
            "str",
            "object",
            "dtype('O')"
          ]
        },
        "meta": {}
      },
      "meta": {},
      "result": {
        "observed_value": "VARCHAR"
      },
      "success": true
    },
    {
      "exception_info": {
        "exception_message": null,
        "exception_traceback": null,
        "raised_exception": false
      },
      "expectation_config": {
        "expectation_type": "expect_column_values_to_be_in_set",
        "kwargs": {
          "batch_id": "216a12aaad3601d000c11f462f93d1e9",
          "column": "last_name",
          "value_set": [
            "A.",
            "B.",
            "C.",
            "D.",
            "E.",
            "F.",
            "G.",
            "H.",
            "J.",
            "K.",
            "L.",
            "M.",
            "N.",
            "O.",
            "P.",
            "R.",
            "S.",
            "T.",
            "W."
          ]
        },
        "meta": {}
      },
      "meta": {},
      "result": {
        "element_count": 100,
        "missing_count": 0,
        "missing_percent": 0.0,
        "partial_unexpected_counts": [],
        "partial_unexpected_index_list": null,
        "partial_unexpected_list": [],
        "unexpected_count": 0,
        "unexpected_percent": 0.0,
        "unexpected_percent_nonmissing": 0.0,
        "unexpected_percent_total": 0.0
      },
      "success": true
    },
    {
      "exception_info": {
        "exception_message": null,
        "exception_traceback": null,
        "raised_exception": false
      },
      "expectation_config": {
        "expectation_type": "expect_column_values_to_not_be_null",
        "kwargs": {
          "batch_id": "216a12aaad3601d000c11f462f93d1e9",
          "column": "last_name"
        },
        "meta": {}
      },
      "meta": {},
      "result": {
        "element_count": 100,
        "partial_unexpected_counts": [],
        "partial_unexpected_index_list": null,
        "partial_unexpected_list": [],
        "unexpected_count": 0,
        "unexpected_percent": 0.0
      },
      "success": true
    },
    {
      "exception_info": {
        "exception_message": null,
        "exception_traceback": null,
        "raised_exception": false
      },
      "expectation_config": {
        "expectation_type": "expect_column_proportion_of_unique_values_to_be_between",
        "kwargs": {
          "batch_id": "216a12aaad3601d000c11f462f93d1e9",
          "column": "last_name",
          "max_value": 0.19,
          "min_value": 0.19
        },
        "meta": {}
      },
      "meta": {},
      "result": {
        "observed_value": 0.19
      },
      "success": true
    },
    {
      "exception_info": {
        "exception_message": null,
        "exception_traceback": null,
        "raised_exception": false
      },
      "expectation_config": {
        "expectation_type": "expect_column_values_to_be_in_type_list",
        "kwargs": {
          "batch_id": "216a12aaad3601d000c11f462f93d1e9",
          "column": "last_name",
          "type_list": [
            "CHAR",
            "NCHAR",
            "VARCHAR",
            "NVARCHAR",
            "TEXT",
            "NTEXT",
            "STRING",
            "StringType",
            "string",
            "str",
            "object",
            "dtype('O')"
          ]
        },
        "meta": {}
      },
      "meta": {},
      "result": {
        "observed_value": "VARCHAR"
      },
      "success": true
    }
  ],
  "statistics": {
    "evaluated_expectations": 17,
    "success_percent": 100.0,
    "successful_expectations": null,
    "unsuccessful_expectations": null
  },
  "success": true
}