{"metadata": {"dbt_schema_version": "https://schemas.getdbt.com/dbt/run-results/v4.json", "dbt_version": "1.1.0", "generated_at": "2022-05-18T23:59:44.825049Z", "invocation_id": "f8575635-f913-445e-8c9b-31560a00ba9c", "env": {}}, "results": [{"status": "success", "timing": [{"name": "compile", "started_at": "2022-05-18T23:59:43.920245Z", "completed_at": "2022-05-18T23:59:43.932720Z"}, {"name": "execute", "started_at": "2022-05-18T23:59:43.938035Z", "completed_at": "2022-05-18T23:59:43.938087Z"}], "thread_id": "Thread-1", "execution_time": 0.025246143341064453, "adapter_response": {}, "message": null, "failures": null, "unique_id": "model.jaffle_shop.stg_jaffle_shop__customers"}, {"status": "success", "timing": [{"name": "compile", "started_at": "2022-05-18T23:59:43.951443Z", "completed_at": "2022-05-18T23:59:43.964667Z"}, {"name": "execute", "started_at": "2022-05-18T23:59:43.968966Z", "completed_at": "2022-05-18T23:59:43.969001Z"}], "thread_id": "Thread-1", "execution_time": 0.024673938751220703, "adapter_response": {}, "message": null, "failures": null, "unique_id": "model.jaffle_shop.stg_jaffle_shop__orders"}, {"status": "success", "timing": [{"name": "compile", "started_at": "2022-05-18T23:59:43.981080Z", "completed_at": "2022-05-18T23:59:43.991768Z"}, {"name": "execute", "started_at": "2022-05-18T23:59:43.995458Z", "completed_at": "2022-05-18T23:59:43.995490Z"}], "thread_id": "Thread-1", "execution_time": 0.021190643310546875, "adapter_response": {}, "message": null, "failures": null, "unique_id": "model.jaffle_shop.stg_stripe__payments"}, {"status": "success", "timing": [{"name": "compile", "started_at": "2022-05-18T23:59:44.004848Z", "completed_at": "2022-05-18T23:59:44.027603Z"}, {"name": "execute", "started_at": "2022-05-18T23:59:44.032199Z", "completed_at": "2022-05-18T23:59:44.032240Z"}], "thread_id": "Thread-1", "execution_time": 0.03293156623840332, "adapter_response": {}, "message": null, "failures": null, "unique_id": "test.jaffle_shop.source_not_null_jaffle_shop_customers_id.50aa22178f"}, {"status": "success", "timing": [{"name": "compile", "started_at": "2022-05-18T23:59:44.044340Z", "completed_at": "2022-05-18T23:59:44.060225Z"}, {"name": "execute", "started_at": "2022-05-18T23:59:44.064914Z", "completed_at": "2022-05-18T23:59:44.064940Z"}], "thread_id": "Thread-1", "execution_time": 0.028696775436401367, "adapter_response": {}, "message": null, "failures": null, "unique_id": "test.jaffle_shop.source_not_null_jaffle_shop_orders_id.f924998b13"}, {"status": "success", "timing": [{"name": "compile", "started_at": "2022-05-18T23:59:44.077448Z", "completed_at": "2022-05-18T23:59:44.099845Z"}, {"name": "execute", "started_at": "2022-05-18T23:59:44.104880Z", "completed_at": "2022-05-18T23:59:44.104935Z"}], "thread_id": "Thread-1", "execution_time": 0.03771400451660156, "adapter_response": {}, "message": null, "failures": null, "unique_id": "test.jaffle_shop.source_not_null_stripe_payment_id.f33f317f6c"}, {"status": "success", "timing": [{"name": "compile", "started_at": "2022-05-18T23:59:44.123971Z", "completed_at": "2022-05-18T23:59:44.148520Z"}, {"name": "execute", "started_at": "2022-05-18T23:59:44.154523Z", "completed_at": "2022-05-18T23:59:44.154723Z"}], "thread_id": "Thread-1", "execution_time": 0.0464174747467041, "adapter_response": {}, "message": null, "failures": null, "unique_id": "test.jaffle_shop.source_unique_jaffle_shop_customers_id.2777a7933e"}, {"status": "success", "timing": [{"name": "compile", "started_at": "2022-05-18T23:59:44.188464Z", "completed_at": "2022-05-18T23:59:44.211335Z"}, {"name": "execute", "started_at": "2022-05-18T23:59:44.216601Z", "completed_at": "2022-05-18T23:59:44.216641Z"}], "thread_id": "Thread-1", "execution_time": 0.04118037223815918, "adapter_response": {}, "message": null, "failures": null, "unique_id": "test.jaffle_shop.source_unique_jaffle_shop_orders_id.8a425b2fba"}, {"status": "success", "timing": [{"name": "compile", "started_at": "2022-05-18T23:59:44.237358Z", "completed_at": "2022-05-18T23:59:44.262953Z"}, {"name": "execute", "started_at": "2022-05-18T23:59:44.270299Z", "completed_at": "2022-05-18T23:59:44.270389Z"}], "thread_id": "Thread-1", "execution_time": 0.045050621032714844, "adapter_response": {}, "message": null, "failures": null, "unique_id": "test.jaffle_shop.source_unique_stripe_payment_id.3b7989ce64"}, {"status": "success", "timing": [{"name": "compile", "started_at": "2022-05-18T23:59:44.293081Z", "completed_at": "2022-05-18T23:59:44.320137Z"}, {"name": "execute", "started_at": "2022-05-18T23:59:44.329470Z", "completed_at": "2022-05-18T23:59:44.329518Z"}], "thread_id": "Thread-1", "execution_time": 0.05153346061706543, "adapter_response": {}, "message": null, "failures": null, "unique_id": "test.jaffle_shop.not_null_stg_jaffle_shop__customers_customer_id.b4343d8610"}, {"status": "success", "timing": [{"name": "compile", "started_at": "2022-05-18T23:59:44.368159Z", "completed_at": "2022-05-18T23:59:44.401553Z"}, {"name": "execute", "started_at": "2022-05-18T23:59:44.408753Z", "completed_at": "2022-05-18T23:59:44.408811Z"}], "thread_id": "Thread-1", "execution_time": 0.06576085090637207, "adapter_response": {}, "message": null, "failures": null, "unique_id": "test.jaffle_shop.unique_stg_jaffle_shop__customers_customer_id.231d91af86"}, {"status": "success", "timing": [{"name": "compile", "started_at": "2022-05-18T23:59:44.445112Z", "completed_at": "2022-05-18T23:59:44.503785Z"}, {"name": "execute", "started_at": "2022-05-18T23:59:44.512068Z", "completed_at": "2022-05-18T23:59:44.512190Z"}], "thread_id": "Thread-1", "execution_time": 0.08485960960388184, "adapter_response": {}, "message": null, "failures": null, "unique_id": "test.jaffle_shop.accepted_values_stg_jaffle_shop__orders_order_status__completed__shipped__returned__return_pending__placed.66bdbafd6b"}, {"status": "success", "timing": [{"name": "compile", "started_at": "2022-05-18T23:59:44.537631Z", "completed_at": "2022-05-18T23:59:44.570068Z"}, {"name": "execute", "started_at": "2022-05-18T23:59:44.576570Z", "completed_at": "2022-05-18T23:59:44.576608Z"}], "thread_id": "Thread-1", "execution_time": 0.05036139488220215, "adapter_response": {}, "message": null, "failures": null, "unique_id": "test.jaffle_shop.not_null_stg_jaffle_shop__orders_order_id.aad0410d08"}, {"status": "success", "timing": [{"name": "compile", "started_at": "2022-05-18T23:59:44.596281Z", "completed_at": "2022-05-18T23:59:44.617584Z"}, {"name": "execute", "started_at": "2022-05-18T23:59:44.622241Z", "completed_at": "2022-05-18T23:59:44.622274Z"}], "thread_id": "Thread-1", "execution_time": 0.040155649185180664, "adapter_response": {}, "message": null, "failures": null, "unique_id": "test.jaffle_shop.relationships_stg_jaffle_shop__orders_customer_id__customer_id__ref_stg_jaffle_shop__customers_.3e222ebf00"}, {"status": "success", "timing": [{"name": "compile", "started_at": "2022-05-18T23:59:44.639110Z", "completed_at": "2022-05-18T23:59:44.654779Z"}, {"name": "execute", "started_at": "2022-05-18T23:59:44.662007Z", "completed_at": "2022-05-18T23:59:44.662098Z"}], "thread_id": "Thread-1", "execution_time": 0.033533334732055664, "adapter_response": {}, "message": null, "failures": null, "unique_id": "test.jaffle_shop.unique_stg_jaffle_shop__orders_order_id.7f899b6afe"}, {"status": "success", "timing": [{"name": "compile", "started_at": "2022-05-18T23:59:44.674744Z", "completed_at": "2022-05-18T23:59:44.688778Z"}, {"name": "execute", "started_at": "2022-05-18T23:59:44.694305Z", "completed_at": "2022-05-18T23:59:44.694349Z"}], "thread_id": "Thread-1", "execution_time": 0.027685880661010742, "adapter_response": {}, "message": null, "failures": null, "unique_id": "model.jaffle_shop.int_orders"}, {"status": "success", "timing": [{"name": "compile", "started_at": "2022-05-18T23:59:44.708771Z", "completed_at": "2022-05-18T23:59:44.722650Z"}, {"name": "execute", "started_at": "2022-05-18T23:59:44.729930Z", "completed_at": "2022-05-18T23:59:44.729964Z"}], "thread_id": "Thread-1", "execution_time": 0.03206181526184082, "adapter_response": {}, "message": null, "failures": null, "unique_id": "test.jaffle_shop.assert_positive_total_for_payments"}, {"status": "success", "timing": [{"name": "compile", "started_at": "2022-05-18T23:59:44.745722Z", "completed_at": "2022-05-18T23:59:44.759770Z"}, {"name": "execute", "started_at": "2022-05-18T23:59:44.764699Z", "completed_at": "2022-05-18T23:59:44.764762Z"}], "thread_id": "Thread-1", "execution_time": 0.026294469833374023, "adapter_response": {}, "message": null, "failures": null, "unique_id": "model.jaffle_shop.fct_customer_orders"}], "elapsed_time": 1.0647211074829102, "args": {"write_json": true, "use_colors": true, "printer_width": 80, "version_check": true, "partial_parse": true, "static_parser": true, "profiles_dir": "/opt/dbt/jaffle_shop", "send_anonymous_usage_stats": true, "event_buffer_size": 100000, "quiet": false, "no_print": false, "project_dir": "/opt/dbt/jaffle_shop", "compile": true, "which": "generate", "rpc_method": "docs.generate", "indirect_selection": "eager"}}